etos_lib/__init__.py
etos_lib/etos.py
etos_lib/eiffel/__init__.py
etos_lib/eiffel/common.py
etos_lib/eiffel/publisher.py
etos_lib/eiffel/subscriber.py
etos_lib/graphql/__init__.py
etos_lib/graphql/query_handler.py
etos_lib/kubernetes/__init__.py
etos_lib/kubernetes/base.py
etos_lib/kubernetes/environment.py
etos_lib/kubernetes/environment_request.py
etos_lib/kubernetes/etos.py
etos_lib/kubernetes/jobs.py
etos_lib/kubernetes/provider.py
etos_lib/kubernetes/testrun.py
etos_lib/kubernetes/schemas/__init__.py
etos_lib/kubernetes/schemas/common.py
etos_lib/kubernetes/schemas/environment.py
etos_lib/kubernetes/schemas/environment_request.py
etos_lib/kubernetes/schemas/provider.py
etos_lib/kubernetes/schemas/testrun.py
etos_lib/lib/__init__.py
etos_lib/lib/config.py
etos_lib/lib/debug.py
etos_lib/lib/events.py
etos_lib/lib/exceptions.py
etos_lib/lib/feature_flags.py
etos_lib/lib/http.py
etos_lib/lib/monitor.py
etos_lib/lib/utils.py
etos_lib/logging/__init__.py
etos_lib/logging/default_config.yaml
etos_lib/logging/filter.py
etos_lib/logging/formatter.py
etos_lib/logging/log_processors.py
etos_lib/logging/log_publisher.py
etos_lib/logging/logger.py
etos_lib/logging/rabbitmq_handler.py
etos_lib/opentelemetry/__init__.py
etos_lib/opentelemetry/semconv.py
etos_lib-5.1.6.dist-info/licenses/LICENSE.txt
etos_lib-5.1.6.dist-info/METADATA
etos_lib-5.1.6.dist-info/WHEEL
etos_lib-5.1.6.dist-info/top_level.txt
etos_lib-5.1.6.dist-info/RECORD
